myFastHistModule/__init__.py
myFastHistModule/fast_histogram.py
myFastHistModule/setup.py
myFastHistModule.egg-info/PKG-INFO
myFastHistModule.egg-info/SOURCES.txt
myFastHistModule.egg-info/dependency_links.txt
myFastHistModule.egg-info/requires.txt
myFastHistModule.egg-info/top_level.txt